Lab_4/Lab4.srcs/sources_1/new/PRNG.v
`timescale 1ns / 1ps
//////////////////////////////////////////////////////////////////////////////////
// UART Transmitter Module (uart_tx)
// Modified to match board constraints:
//   • Clock input renamed to sysclk
//   • UART TX output renamed to uart_txd_in
//////////////////////////////////////////////////////////////////////////////////
module seed_provider (
    output [31:0] C1_seed,
    output [31:0] C2_seed,
    output [31:0] L_seed
);
    // Example static assignment or logic to generate seeds
    assign C1_seed = 32'hA5A5A5A5;
    assign C2_seed = 32'h5A5A5A5A;
    assign L_seed  = 32'hDEADBEEF;
endmodule

module uart_tx (
    input        sysclk,       // was clk
    input        rst,
    input        tx_start,         // pulse to start transmission
    input  [7:0] tx_data,          // data to transmit
    output reg   uart_txd_in,      // renamed to match XDC constraint
    output reg   tx_done           // asserted for one cycle when transmission finishes
);
  // Parameters: change these as needed.
  parameter CLOCK_FREQ = 50000000;  // 50 MHz clock
  parameter BAUD_RATE  = 115200;    // desired baud rate
  localparam BAUD_TICK = CLOCK_FREQ / BAUD_RATE;

  reg [15:0] baud_counter;
  reg [3:0]  bit_index;
  reg [9:0]  tx_shift;             // [0]: start, [1]-[8]: data, [9]: stop
  reg        sending;

  always @(posedge sysclk or posedge rst) begin
    if (rst) begin
      baud_counter <= 0;
      bit_index    <= 0;
      tx_shift     <= 10'b1111111111;
      uart_txd_in  <= 1;  // Idle state is high
      sending      <= 0;
      tx_done      <= 0;
    end else begin
      if (tx_start && !sending) begin
        // Load shift register with frame: start bit (0), 8 data bits (LSB first), stop bit (1)
        tx_shift <= {1'b1, tx_data, 1'b0};
        sending  <= 1;
        baud_counter <= 0;
        bit_index <= 0;
        tx_done <= 0;
      end else if (sending) begin
        if (baud_counter < BAUD_TICK - 1) begin
          baud_counter <= baud_counter + 1;
        end else begin
          baud_counter <= 0;
          uart_txd_in <= tx_shift[bit_index];
          if (bit_index < 9) begin
            bit_index <= bit_index + 1;
          end else begin
            sending   <= 0;
            tx_done   <= 1;
          end
        end
      end else begin
        tx_done <= 0;
      end
    end
  end
endmodule

//////////////////////////////////////////////////////////////////////////////////
// Chua RNG Module (chua_rng)
// Digital simulation of Chua's circuit using Euler integration.
// Generates a 16-bit random number by extracting the lower 16 bits of v1.
// Fixed-point format: Q16 (32-bit signed; 16 integer and 16 fractional bits)
//////////////////////////////////////////////////////////////////////////////////
module chua_rng (
    input              sysclk,   // renamed from clk
    input              rst,      // synchronous reset (active high)
    output reg [15:0]  rnd       // 16-bit random number output
);
  // State registers: Q16 fixed-point (32-bit signed)
  reg signed [31:0] v1;  // voltage across C1
  reg signed [31:0] v2;  // voltage across C2
  reg signed [31:0] iL;  // current through the inductor
  
  wire [31:0] C1_seed;
  wire [31:0] C2_seed;
  wire [31:0] L_seed;
  
  seed_provider seeds (
        .C1_seed(C1_seed),
        .C2_seed(C2_seed),
        .L_seed(L_seed)
    );

  // Parameter definitions (in Q16 format)

  parameter signed [31:0] inv_C1 = 32'd6554;   // ~65536/10
  parameter signed [31:0] inv_C2 = 32'd655;    // ~65536/100
  parameter signed [31:0] inv_L  = 32'd3641;   // ~65536/18

  parameter signed [31:0] R  = 32'd10000;  // resistor value (Q16)
  parameter signed [31:0] dt = 32'd66;      // time step ≈0.001 in Q16 (66/65536)
  // Nonlinear resistor (Chua diode) parameters in Q16.
  parameter signed [31:0] Ga = -32'd49152; // approx. -0.75 in Q16
  parameter signed [31:0] Gb =  32'd32768; // approx. 0.5 in Q16
  parameter signed [31:0] B  =  32'd8192;  // approx. 0.125 in Q16

  // Nonlinear function for Chua's diode (piecewise-linear)
  function signed [31:0] nonlinear;
    input signed [31:0] x;
    begin
      if (x > B)
        nonlinear = (Gb * x) >>> 16;
      else if (x < -B)
        nonlinear = (Gb * x) >>> 16;
      else
        nonlinear = (Ga * x) >>> 16;
    end
  endfunction

  reg signed [31:0] dv1, dv2, diL;
  reg signed [31:0] diff; // (v1 - v2)
  reg signed [31:0] term; // temporary term

  always @(posedge sysclk or posedge rst) begin
    if (rst) begin
      // Initialize state registers: seed values scaled to Q16.
      v1  <= C1_seed << 16;
      v2  <= C2_seed << 16;
      iL  <= L_seed  << 16;
      rnd <= 16'h0000;
    end else begin
      diff = v1 - v2;
      term = diff / R;
      dv1 = (inv_C1 * (term - nonlinear(v1))) >> 16;
      dv2 = (inv_C2 * ((-diff) / R + iL)) >> 16;
      diL = (inv_L * (-v2)) >> 16;

      // Euler integration update
      v1  <= v1  + ((dt * dv1) >> 16);
      v2  <= v2  + ((dt * dv2) >> 16);
      iL  <= iL  + ((dt * diL) >> 16);

      // Use lower 16 bits of v1 as random output
      rnd <= v1[15:0];
    end
  end
endmodule

//////////////////////////////////////////////////////////////////////////////////
// Top-Level Module (chua_uart_rng)
// Instantiates the Chua RNG and a UART transmitter.
// It latches a new 16-bit random number from the Chua simulation and sends it out via UART
// as two sequential 8-bit bytes (high byte first, then low byte).
// Ports are renamed to match the XDC constraint file:
//  - Clock input is now sysclk.
//  - UART TX output is now uart_txd_in.
//  - A dummy UART RX input, uart_rxd_out, is added.
//////////////////////////////////////////////////////////////////////////////////
module chua_uart_rng (
    input        sysclk,          // renamed from clk
    input        rst,
    output       uart_txd_in,     // matches constraint for UART TX output
    input        uart_rxd_out     // dummy port to satisfy board constraints; unused in this design
);
  // Wire from Chua RNG.
  wire [15:0] rnd;
  reg [15:0]  random_value;

  chua_rng rng_inst (
      .sysclk(sysclk),
      .rst(rst),
      .rnd(rnd)
  );

  // Signals for UART transmission.
  reg         tx_start;
  reg  [7:0]  tx_data;
  wire        tx_done;

  uart_tx uart_tx_inst (
      .sysclk(sysclk),
      .rst(rst),
      .tx_start(tx_start),
      .tx_data(tx_data),
      .uart_txd_in(uart_txd_in),
      .tx_done(tx_done)
  );

  // FSM to transmit the 16-bit random number in two sequential 8-bit segments.
  localparam STATE_IDLE       = 0;
  localparam STATE_SEND_HIGH  = 1;
  localparam STATE_WAIT_HIGH  = 2;
  localparam STATE_SEND_LOW   = 3;
  localparam STATE_WAIT_LOW   = 4;
  localparam STATE_DELAY      = 5;

  reg [2:0] state;
  reg [23:0] delay_counter; // Delay between transmissions.

  always @(posedge sysclk or posedge rst) begin
    if (rst) begin
      state         <= STATE_IDLE;
      tx_start      <= 0;
      tx_data       <= 8'd0;
      random_value  <= 16'd0;
      delay_counter <= 0;
    end else begin
      case (state)
        STATE_IDLE: begin
          // Latch current random value.
          random_value <= rnd;
          // Begin transmitting the high byte.
          tx_data  <= rnd[15:8];
          tx_start <= 1;
          state    <= STATE_SEND_HIGH;
        end
        STATE_SEND_HIGH: begin
          tx_start <= 0; // Clear start pulse.
          state    <= STATE_WAIT_HIGH;
        end
        STATE_WAIT_HIGH: begin
          if (tx_done) begin
            // High byte sent; now load low byte.
            tx_data  <= random_value[7:0];
            tx_start <= 1;
            state    <= STATE_SEND_LOW;
          end
        end
        STATE_SEND_LOW: begin
          tx_start <= 0;
          state    <= STATE_WAIT_LOW;
        end
        STATE_WAIT_LOW: begin
          if (tx_done) begin
            state         <= STATE_DELAY;
            delay_counter <= 0;
          end
        end
        STATE_DELAY: begin
          if (delay_counter < 24'd5000000) begin // Adjust delay as needed.
            delay_counter <= delay_counter + 1;
          end else begin
            state <= STATE_IDLE;
          end
        end
        default: state <= STATE_IDLE;
      endcase
    end
  end
endmodule

Lab_4/Lab4.srcs/sim_1/new/testbench.v
//////////////////////////////////////////////////////////////////////////////////
// Company: 
// Engineer: 
// 
// Create Date: 10.04.2025 12:40:17
// Design Name: 
// Module Name: testbench
// Project Name: 
// Target Devices: 
// Tool Versions: 
// Description: 
// 
// Dependencies: 
// 
// Revision:
// Revision 0.01 - File Created
// Additional Comments:
// 
//////////////////////////////////////////////////////////////////////////////////


`timescale 1ns/1ps
module tb_chua_uart_rng;
  // Declare testbench signals.
  reg         sysclk;
  reg         rst;
  wire [15:0] rnd_out;

  // Instantiate the Chua RNG module.
  chua_rng rng_uut (
    .sysclk(sysclk),
    .rst(rst),
    .rnd(rnd_out)
  );

  // Combined initial block using one for loop.
  initial begin
    // Initialize values.
    sysclk = 0;

    rst = 0;

    // Dump all variables for waveform inspection.
    $dumpfile("simulation.vcd");
    $dumpvars(0, tb_chua_uart_rng);

    // Run the simulation loop. 
    // For example, if you want to run for 10,000,000 ns using a 5 ns time step:
    // Total iterations = 10,000,000 ns / 5 ns = 2,000,000 iterations.
    for (integer i = 0; i < 2000000; i = i + 1) begin
      #5;                 // Delay of 5 ns per iteration.
      sysclk = ~sysclk;   // Toggle the clock every 5 ns.

      // Update seed_2 every 10 ns.
      // Since our time step is 5 ns, do it on every second iteration.
      if (i % 2 == 0)


      // Toggle reset every 40 ns.
      // (40 ns / 5 ns = 8 iterations; every 8 iterations, toggle rst).
      if (i % 8 == 0)
        rst = ~rst;
    end

    // End simulation
    $stop;
  end

endmodule

Lab_4/Lab4.sim/sim_1/behav/xsim/simulation.vcd
$date
   Mon Apr 14 22:56:36 2025
$end

$version
  2024.2.0
  $dumpfile ("simulation.vcd") 
$end

$timescale
  1ps
$end

$scope module tb_chua_uart_rng $end
$var reg 1 ! sysclk $end
$var reg 1 " rst $end
$var wire 16 # rnd_out [15:0] $end
$scope module rng_uut $end
$var wire 1 $ sysclk $end
$var wire 1 % rst $end
$var reg 16 & rnd [15:0] $end
$var reg 32 ' v1 [31:0] $end
$var reg 32 ( v2 [31:0] $end
$var reg 32 ) iL [31:0] $end
$var wire 32 * C1_seed [31:0] $end
$var wire 32 + C2_seed [31:0] $end
$var wire 32 , L_seed [31:0] $end
$var reg 32 - dv1 [31:0] $end
$var reg 32 . dv2 [31:0] $end
$var reg 32 / diL [31:0] $end
$var reg 32 0 diff [31:0] $end
$var reg 32 1 term [31:0] $end
$scope module seeds $end
$var wire 32 * C1_seed [31:0] $end
$var wire 32 + C2_seed [31:0] $end
$var wire 32 , L_seed [31:0] $end
$upscope $end
$scope function nonlinear $end
$var reg 32 2 nonlinear [31:0] $end
$var reg 32 3 x [31:0] $end
$upscope $end
$upscope $end
$scope begin Block50_2 $end
$var integer 32 4 i [31:0] $end
$upscope $end
$upscope $end
$enddefinitions $end

#0
$dumpvars
0!
0"
bx #
0$
0%
bx &
bx '
bx (
bx )
b10100101101001011010010110100101 *
b1011010010110100101101001011010 +
b11011110101011011011111011101111 ,
bx -
bx .
bx /
bx 0
bx 1
bx 2
bx 3
b0 4
$end

#5000
1!
1"
b0 #
1$
1%
b0 &
b10100101101001010000000000000000 '
b1011010010110100000000000000000 (
b10111110111011110000000000000000 )
b1 4

#10000
0!
0$
b10 4

#15000
1!
1$
b11 4

#20000
0!
0$
b100 4

#25000
1!
1$
b101 4

#30000
0!
0$
b110 4

#35000
1!
1$
b111 4

#40000
0!
0$
b1000 4

#45000
1!
0"
1$
0%
b10100101101001010000000000010000 '
b1011010010110100000000000100001 (
b10111110111011110000000000111111 )
b11111000100101 -
b1000000010010010 .
b1111010111110110 /
b1001011010010110000000000000000 0
b11110110101110000 1
b11111111111111111000000000000000 2
b10100101101001010000000000000000 3
b1001 4

#50000
0!
0$
b1010 4

#55000
1!
b10000 #
1$
b10000 &
b10100101101001010000000000100000 '
b1011010010110100000000001000010 (
b10111110111011110000000001111110 )
b11111000100100 -
b1000000010010011 .
b1111010111110100 /
b1001011010010101111111111101111 0
b11111111111111111000000000001000 2
b10100101101001010000000000010000 3
b1011 4

#60000
0!
0$
b1100 4

#65000
1!
b100000 #
1$
b100000 &
b10100101101001010000000000110000 '
b1011010010110100000000001100011 (
b10111110111011110000000010111101 )
b1111010111110010 /
b1001011010010101111111111011110 0
b11111111111111111000000000010000 2
b10100101101001010000000000100000 3
b1101 4

#70000
0!
0$
b1110 4

#75000
1!
b110000 #
1$
b110000 &
b10100101101001010000000001000000 '
b1011010010110100000000010000100 (
b10111110111011110000000011111100 )
b11111000100011 -
b1000000010010100 .
b1111010111110000 /
b1001011010010101111111111001101 0
b11111111111111111000000000011000 2
b10100101101001010000000000110000 3
b1111 4

#80000
0!
0$
b10000 4

#85000
1!
1"
b0 #
1$
1%
b0 &
b10100101101001010000000000000000 '
b1011010010110100000000000000000 (
b10111110111011110000000000000000 )
b10001 4

#90000
0!
0$
b10010 4

#95000
1!
1$
b10011 4

#100000
0!
0$
b10100 4

#105000
1!
1$
b10101 4

#110000
0!
0$
b10110 4

#115000
1!
1$
b10111 4

#120000
0!
0$
b11000 4

#125000
1!
0"
1$
0%
b10100101101001010000000000010000 '
b1011010010110100000000000100001 (
b10111110111011110000000000111111 )
b11111000100101 -
b1000000010010010 .
b1111010111110110 /
b1001011010010110000000000000000 0
b11111111111111111000000000000000 2
b10100101101001010000000000000000 3
b11001 4

#130000
0!
0$
b11010 4

#135000
1!
b10000 #
1$
b10000 &
b10100101101001010000000000100000 '
b1011010010110100000000001000010 (
b10111110111011110000000001111110 )
b11111000100100 -
b1000000010010011 .
b1111010111110100 /
b1001011010010101111111111101111 0
b11111111111111111000000000001000 2
b10100101101001010000000000010000 3
b11011 4

#140000
0!
0$
b11100 4

#145000
1!
b100000 #
1$
b100000 &
b10100101101001010000000000110000 '
b1011010010110100000000001100011 (
b10111110111011110000000010111101 )
b1111010111110010 /
b1001011010010101111111111011110 0
b11111111111111111000000000010000 2
b10100101101001010000000000100000 3
b11101 4

#150000
0!
0$
b11110 4

#155000
1!
b110000 #
1$
b110000 &
b10100101101001010000000001000000 '
b1011010010110100000000010000100 (
b10111110111011110000000011111100 )
b11111000100011 -
b1000000010010100 .
b1111010111110000 /
b1001011010010101111111111001101 0
b11111111111111111000000000011000 2
b10100101101001010000000000110000 3
b11111 4

#160000
0!
0$
b100000 4

#165000
1!
1"
b0 #
1$
1%
b0 &
b10100101101001010000000000000000 '
b1011010010110100000000000000000 (
b10111110111011110000000000000000 )
b100001 4

#170000
0!
0$
b100010 4

#175000
1!
1$
b100011 4

#180000
0!
0$
b100100 4

#185000
1!
1$
b100101 4

#190000
0!
0$
b100110 4

#195000
1!
1$
b100111 4

#200000
0!
0$
b101000 4

#205000
1!
0"
1$
0%
b10100101101001010000000000010000 '
b1011010010110100000000000100001 (
b10111110111011110000000000111111 )
b11111000100101 -
b1000000010010010 .
b1111010111110110 /
b1001011010010110000000000000000 0
b11111111111111111000000000000000 2
b10100101101001010000000000000000 3
b101001 4

#210000
0!
0$
b101010 4

#215000
1!
b10000 #
1$
b10000 &
b10100101101001010000000000100000 '
b1011010010110100000000001000010 (
b10111110111011110000000001111110 )
b11111000100100 -
b1000000010010011 .
b1111010111110100 /
b1001011010010101111111111101111 0
b11111111111111111000000000001000 2
b10100101101001010000000000010000 3
b101011 4

#220000
0!
0$
b101100 4

#225000
1!
b100000 #
1$
b100000 &
b10100101101001010000000000110000 '
b1011010010110100000000001100011 (
b10111110111011110000000010111101 )
b1111010111110010 /
b1001011010010101111111111011110 0
b11111111111111111000000000010000 2
b10100101101001010000000000100000 3
b101101 4

#230000
0!
0$
b101110 4

#235000
1!
b110000 #
1$
b110000 &
b10100101101001010000000001000000 '
b1011010010110100000000010000100 (
b10111110111011110000000011111100 )
b11111000100011 -
b1000000010010100 .
b1111010111110000 /
b1001011010010101111111111001101 0
b11111111111111111000000000011000 2
b10100101101001010000000000110000 3
b101111 4

#240000
0!
0$
b110000 4

#245000
1!
1"
b0 #
1$
1%
b0 &
b10100101101001010000000000000000 '
b1011010010110100000000000000000 (
b10111110111011110000000000000000 )
b110001 4

#250000
0!
0$
b110010 4

#255000
1!
1$
b110011 4

#260000
0!
0$
b110100 4

#265000
1!
1$
b110101 4

#270000
0!
0$
b110110 4

#275000
1!
1$
b110111 4

#280000
0!
0$
b111000 4

#285000
1!
0"
1$
0%
b10100101101001010000000000010000 '
b1011010010110100000000000100001 (
b10111110111011110000000000111111 )
b11111000100101 -
b1000000010010010 .
b1111010111110110 /
b1001011010010110000000000000000 0
b11111111111111111000000000000000 2
b10100101101001010000000000000000 3
b111001 4

#290000
0!
0$
b111010 4

#295000
1!
b10000 #
1$
b10000 &
b10100101101001010000000000100000 '
b1011010010110100000000001000010 (
b10111110111011110000000001111110 )
b11111000100100 -
b1000000010010011 .
b1111010111110100 /
b1001011010010101111111111101111 0
b11111111111111111000000000001000 2
b10100101101001010000000000010000 3
b111011 4

#300000
0!
0$
b111100 4

#305000
1!
b100000 #
1$
b100000 &
b10100101101001010000000000110000 '
b1011010010110100000000001100011 (
b10111110111011110000000010111101 )
b1111010111110010 /
b1001011010010101111111111011110 0
b11111111111111111000000000010000 2
b10100101101001010000000000100000 3
b111101 4

#310000
0!
0$
b111110 4

#315000
1!
b110000 #
1$
b110000 &
b10100101101001010000000001000000 '
b1011010010110100000000010000100 (
b10111110111011110000000011111100 )
b11111000100011 -
b1000000010010100 .
b1111010111110000 /
b1001011010010101111111111001101 0
b11111111111111111000000000011000 2
b10100101101001010000000000110000 3
b111111 4

#320000
0!
0$
b1000000 4

#325000
1!
1"
b0 #
1$
1%
b0 &
b10100101101001010000000000000000 '
b1011010010110100000000000000000 (
b10111110111011110000000000000000 )
b1000001 4

#330000
0!
0$
b1000010 4

#335000
1!
1$
b1000011 4

#340000
0!
0$
b1000100 4

#345000
1!
1$
b1000101 4

#350000
0!
0$
b1000110 4

#355000
1!
1$
b1000111 4

#360000
0!
0$
b1001000 4

#365000
1!
0"
1$
0%
b10100101101001010000000000010000 '
b1011010010110100000000000100001 (
b10111110111011110000000000111111 )
b11111000100101 -
b1000000010010010 .
b1111010111110110 /
b1001011010010110000000000000000 0
b11111111111111111000000000000000 2
b10100101101001010000000000000000 3
b1001001 4

#370000
0!
0$
b1001010 4

#375000
1!
b10000 #
1$
b10000 &
b10100101101001010000000000100000 '
b1011010010110100000000001000010 (
b10111110111011110000000001111110 )
b11111000100100 -
b1000000010010011 .
b1111010111110100 /
b1001011010010101111111111101111 0
b11111111111111111000000000001000 2
b10100101101001010000000000010000 3
b1001011 4

#380000
0!
0$
b1001100 4

#385000
1!
b100000 #
1$
b100000 &
b10100101101001010000000000110000 '
b1011010010110100000000001100011 (
b10111110111011110000000010111101 )
b1111010111110010 /
b1001011010010101111111111011110 0
b11111111111111111000000000010000 2
b10100101101001010000000000100000 3
b1001101 4

#390000
0!
0$
b1001110 4

#395000
1!
b110000 #
1$
b110000 &
b10100101101001010000000001000000 '
b1011010010110100000000010000100 (
b10111110111011110000000011111100 )
b11111000100011 -
b1000000010010100 .
b1111010111110000 /
b1001011010010101111111111001101 0
b11111111111111111000000000011000 2
b10100101101001010000000000110000 3
b1001111 4

#400000
0!
0$
b1010000 4

#405000
1!
1"
b0 #
1$
1%
b0 &
b10100101101001010000000000000000 '
b1011010010110100000000000000000 (
b10111110111011110000000000000000 )
b1010001 4

#410000
0!
0$
b1010010 4

#415000
1!
1$
b1010011 4

#420000
0!
0$
b1010100 4

#425000
1!
1$
b1010101 4

#430000
0!
0$
b1010110 4

#435000
1!
1$
b1010111 4

#440000
0!
0$
b1011000 4

#445000
1!
0"
1$
0%
b10100101101001010000000000010000 '
b1011010010110100000000000100001 (
b10111110111011110000000000111111 )
b11111000100101 -
b1000000010010010 .
b1111010111110110 /
b1001011010010110000000000000000 0
b11111111111111111000000000000000 2
b10100101101001010000000000000000 3
b1011001 4

#450000
0!
0$
b1011010 4

#455000
1!
b10000 #
1$
b10000 &
b10100101101001010000000000100000 '
b1011010010110100000000001000010 (
b10111110111011110000000001111110 )
b11111000100100 -
b1000000010010011 .
b1111010111110100 /
b1001011010010101111111111101111 0
b11111111111111111000000000001000 2
b10100101101001010000000000010000 3
b1011011 4

#460000
0!
0$
b1011100 4

#465000
1!
b100000 #
1$
b100000 &
b10100101101001010000000000110000 '
b1011010010110100000000001100011 (
b10111110111011110000000010111101 )
b1111010111110010 /
b1001011010010101111111111011110 0
b11111111111111111000000000010000 2
b10100101101001010000000000100000 3
b1011101 4

#470000
0!
0$
b1011110 4

#475000
1!
b110000 #
1$
b110000 &
b10100101101001010000000001000000 '
b1011010010110100000000010000100 (
b10111110111011110000000011111100 )
b11111000100011 -
b1000000010010100 .
b1111010111110000 /
b1001011010010101111111111001101 0
b11111111111111111000000000011000 2
b10100101101001010000000000110000 3
b1011111 4

#480000
0!
0$
b1100000 4

#485000
1!
1"
b0 #
1$
1%
b0 &
b10100101101001010000000000000000 '
b1011010010110100000000000000000 (
b10111110111011110000000000000000 )
b1100001 4

#490000
0!
0$
b1100010 4

#495000
1!
1$
b1100011 4

#500000
0!
0$
b1100100 4

#505000
1!
1$
b1100101 4

#510000
0!
0$
b1100110 4

#515000
1!
1$
b1100111 4

#520000
0!
0$
b1101000 4

#525000
1!
0"
1$
0%
b10100101101001010000000000010000 '
b1011010010110100000000000100001 (
b10111110111011110000000000111111 )
b11111000100101 -
b1000000010010010 .
b1111010111110110 /
b1001011010010110000000000000000 0
b11111111111111111000000000000000 2
b10100101101001010000000000000000 3
b1101001 4

#530000
0!
0$
b1101010 4

#535000
1!
b10000 #
1$
b10000 &
b10100101101001010000000000100000 '
b1011010010110100000000001000010 (
b10111110111011110000000001111110 )
b11111000100100 -
b1000000010010011 .
b1111010111110100 /
b1001011010010101111111111101111 0
b11111111111111111000000000001000 2
b10100101101001010000000000010000 3
b1101011 4

#540000
0!
0$
b1101100 4

#545000
1!
b100000 #
1$
b100000 &
b10100101101001010000000000110000 '
b1011010010110100000000001100011 (
b10111110111011110000000010111101 )
b1111010111110010 /
b1001011010010101111111111011110 0
b11111111111111111000000000010000 2
b10100101101001010000000000100000 3
b1101101 4

#550000
0!
0$
b1101110 4

#555000
1!
b110000 #
1$
b110000 &
b10100101101001010000000001000000 '
b1011010010110100000000010000100 (
b10111110111011110000000011111100 )
b11111000100011 -
b1000000010010100 .
b1111010111110000 /
b1001011010010101111111111001101 0
b11111111111111111000000000011000 2
b10100101101001010000000000110000 3
b1101111 4

#560000
0!
0$
b1110000 4

#565000
1!
1"
b0 #
1$
1%
b0 &
b10100101101001010000000000000000 '
b1011010010110100000000000000000 (
b10111110111011110000000000000000 )
b1110001 4

#570000
0!
0$
b1110010 4

#575000
1!
1$
b1110011 4

#580000
0!
0$
b1110100 4

#585000
1!
1$
b1110101 4

#590000
0!
0$
b1110110 4

#595000
1!
1$
b1110111 4

#600000
0!
0$
b1111000 4

#605000
1!
0"
1$
0%
b10100101101001010000000000010000 '
b1011010010110100000000000100001 (
b10111110111011110000000000111111 )
b11111000100101 -
b1000000010010010 .
b1111010111110110 /
b1001011010010110000000000000000 0
b11111111111111111000000000000000 2
b10100101101001010000000000000000 3
b1111001 4

#610000
0!
0$
b1111010 4

#615000
1!
b10000 #
1$
b10000 &
b10100101101001010000000000100000 '
b1011010010110100000000001000010 (
b10111110111011110000000001111110 )
b11111000100100 -
b1000000010010011 .
b1111010111110100 /
b1001011010010101111111111101111 0
b11111111111111111000000000001000 2
b10100101101001010000000000010000 3
b1111011 4

#620000
0!
0$
b1111100 4

#625000
1!
b100000 #
1$
b100000 &
b10100101101001010000000000110000 '
b1011010010110100000000001100011 (
b10111110111011110000000010111101 )
b1111010111110010 /
b1001011010010101111111111011110 0
b11111111111111111000000000010000 2
b10100101101001010000000000100000 3
b1111101 4

#630000
0!
0$
b1111110 4

#635000
1!
b110000 #
1$
b110000 &
b10100101101001010000000001000000 '
b1011010010110100000000010000100 (
b10111110111011110000000011111100 )
b11111000100011 -
b1000000010010100 .
b1111010111110000 /
b1001011010010101111111111001101 0
b11111111111111111000000000011000 2
b10100101101001010000000000110000 3
b1111111 4

#640000
0!
0$
b10000000 4

#645000
1!
1"
b0 #
1$
1%
b0 &
b10100101101001010000000000000000 '
b1011010010110100000000000000000 (
b10111110111011110000000000000000 )
b10000001 4

#650000
0!
0$
b10000010 4

#655000
1!
1$
b10000011 4

#660000
0!
0$
b10000100 4

#665000
1!
1$
b10000101 4

#670000
0!
0$
b10000110 4

#675000
1!
1$
b10000111 4

#680000
0!
0$
b10001000 4

#685000
1!
0"
1$
0%
b10100101101001010000000000010000 '
b1011010010110100000000000100001 (
b10111110111011110000000000111111 )
b11111000100101 -
b1000000010010010 .
b1111010111110110 /
b1001011010010110000000000000000 0
b11111111111111111000000000000000 2
b10100101101001010000000000000000 3
b10001001 4

#690000
0!
0$
b10001010 4

#695000
1!
b10000 #
1$
b10000 &
b10100101101001010000000000100000 '
b1011010010110100000000001000010 (
b10111110111011110000000001111110 )
b11111000100100 -
b1000000010010011 .
b1111010111110100 /
b1001011010010101111111111101111 0
b11111111111111111000000000001000 2
b10100101101001010000000000010000 3
b10001011 4

#700000
0!
0$
b10001100 4

#705000
1!
b100000 #
1$
b100000 &
b10100101101001010000000000110000 '
b1011010010110100000000001100011 (
b10111110111011110000000010111101 )
b1111010111110010 /
b1001011010010101111111111011110 0
b11111111111111111000000000010000 2
b10100101101001010000000000100000 3
b10001101 4

#710000
0!
0$
b10001110 4

#715000
1!
b110000 #
1$
b110000 &
b10100101101001010000000001000000 '
b1011010010110100000000010000100 (
b10111110111011110000000011111100 )
b11111000100011 -
b1000000010010100 .
b1111010111110000 /
b1001011010010101111111111001101 0
b11111111111111111000000000011000 2
b10100101101001010000000000110000 3
b10001111 4

#720000
0!
0$
b10010000 4

#725000
1!
1"
b0 #
1$
1%
b0 &
b10100101101001010000000000000000 '
b1011010010110100000000000000000 (
b10111110111011110000000000000000 )
b10010001 4

#730000
0!
0$
b10010010 4

#735000
1!
1$
b10010011 4

#740000
0!
0$
b10010100 4

#745000
1!
1$
b10010101 4

#750000
0!
0$
b10010110 4

#755000
1!
1$
b10010111 4

#760000
0!
0$
b10011000 4

#765000
1!
0"
1$
0%
b10100101101001010000000000010000 '
b1011010010110100000000000100001 (
b10111110111011110000000000111111 )
b11111000100101 -
b1000000010010010 .
b1111010111110110 /
b1001011010010110000000000000000 0
b11111111111111111000000000000000 2
b10100101101001010000000000000000 3
b10011001 4

#770000
0!
0$
b10011010 4

#775000
1!
b10000 #
1$
b10000 &
b10100101101001010000000000100000 '
b1011010010110100000000001000010 (
b10111110111011110000000001111110 )
b11111000100100 -
b1000000010010011 .
b1111010111110100 /
b1001011010010101111111111101111 0
b11111111111111111000000000001000 2
b10100101101001010000000000010000 3
b10011011 4

#780000
0!
0$
b10011100 4

#785000
1!
b100000 #
1$
b100000 &
b10100101101001010000000000110000 '
b1011010010110100000000001100011 (
b10111110111011110000000010111101 )
b1111010111110010 /
b1001011010010101111111111011110 0
b11111111111111111000000000010000 2
b10100101101001010000000000100000 3
b10011101 4

#790000
0!
0$
b10011110 4

#795000
1!
b110000 #
1$
b110000 &
b10100101101001010000000001000000 '
b1011010010110100000000010000100 (
b10111110111011110000000011111100 )
b11111000100011 -
b1000000010010100 .
b1111010111110000 /
b1001011010010101111111111001101 0
b11111111111111111000000000011000 2
b10100101101001010000000000110000 3
b10011111 4

#800000
0!
0$
b10100000 4

#805000
1!
1"
b0 #
1$
1%
b0 &
b10100101101001010000000000000000 '
b1011010010110100000000000000000 (
b10111110111011110000000000000000 )
b10100001 4

#810000
0!
0$
b10100010 4

#815000
1!
1$
b10100011 4

#820000
0!
0$
b10100100 4

#825000
1!
1$
b10100101 4

#830000
0!
0$
b10100110 4

#835000
1!
1$
b10100111 4

#840000
0!
0$
b10101000 4

#845000
1!
0"
1$
0%
b10100101101001010000000000010000 '
b1011010010110100000000000100001 (
b10111110111011110000000000111111 )
b11111000100101 -
b1000000010010010 .
b1111010111110110 /
b1001011010010110000000000000000 0
b11111111111111111000000000000000 2
b10100101101001010000000000000000 3
b10101001 4

#850000
0!
0$
b10101010 4

#855000
1!
b10000 #
1$
b10000 &
b10100101101001010000000000100000 '
b1011010010110100000000001000010 (
b10111110111011110000000001111110 )
b11111000100100 -
b1000000010010011 .
b1111010111110100 /
b1001011010010101111111111101111 0
b11111111111111111000000000001000 2
b10100101101001010000000000010000 3
b10101011 4

#860000
0!
0$
b10101100 4

#865000
1!
b100000 #
1$
b100000 &
b10100101101001010000000000110000 '
b1011010010110100000000001100011 (
b10111110111011110000000010111101 )
b1111010111110010 /
b1001011010010101111111111011110 0
b11111111111111111000000000010000 2
b10100101101001010000000000100000 3
b10101101 4

#870000
0!
0$
b10101110 4

#875000
1!
b110000 #
1$
b110000 &
b10100101101001010000000001000000 '
b1011010010110100000000010000100 (
b10111110111011110000000011111100 )
b11111000100011 -
b1000000010010100 .
b1111010111110000 /
b1001011010010101111111111001101 0
b11111111111111111000000000011000 2
b10100101101001010000000000110000 3
b10101111 4

#880000
0!
0$
b10110000 4

#885000
1!
1"
b0 #
1$
1%
b0 &
b10100101101001010000000000000000 '
b1011010010110100000000000000000 (
b10111110111011110000000000000000 )
b10110001 4

#890000
0!
0$
b10110010 4

#895000
1!
1$
b10110011 4

#900000
0!
0$
b10110100 4

#905000
1!
1$
b10110101 4

#910000
0!
0$
b10110110 4

#915000
1!
1$
b10110111 4

#920000
0!
0$
b10111000 4

#925000
1!
0"
1$
0%
b10100101101001010000000000010000 '
b1011010010110100000000000100001 (
b10111110111011110000000000111111 )
b11111000100101 -
b1000000010010010 .
b1111010111110110 /
b1001011010010110000000000000000 0
b11111111111111111000000000000000 2
b10100101101001010000000000000000 3
b10111001 4

#930000
0!
0$
b10111010 4

#935000
1!
b10000 #
1$
b10000 &
b10100101101001010000000000100000 '
b1011010010110100000000001000010 (
b10111110111011110000000001111110 )
b11111000100100 -
b1000000010010011 .
b1111010111110100 /
b1001011010010101111111111101111 0
b11111111111111111000000000001000 2
b10100101101001010000000000010000 3
b10111011 4

#940000
0!
0$
b10111100 4

#945000
1!
b100000 #
1$
b100000 &
b10100101101001010000000000110000 '
b1011010010110100000000001100011 (
b10111110111011110000000010111101 )
b1111010111110010 /
b1001011010010101111111111011110 0
b11111111111111111000000000010000 2
b10100101101001010000000000100000 3
b10111101 4

#950000
0!
0$
b10111110 4

