Lab_4/Lab4.srcs/sources_1/new/PRNG.v
`timescale 1ns / 1ps
//////////////////////////////////////////////////////////////////////////////////
// UART Transmitter Module (uart_tx)
// Modified to match board constraints:
//   • Clock input renamed to sysclk
//   • UART TX output renamed to uart_txd_in
//////////////////////////////////////////////////////////////////////////////////
module uart_tx (
    input        sysclk,       // was clk
    input        rst,
    input        tx_start,         // pulse to start transmission
    input  [7:0] tx_data,          // data to transmit
    output reg   uart_txd_in,      // renamed to match XDC constraint
    output reg   tx_done           // asserted for one cycle when transmission finishes
);
  // Parameters: change these as needed.
  parameter CLOCK_FREQ = 50000000;  // 50 MHz clock
  parameter BAUD_RATE  = 115200;    // desired baud rate
  localparam BAUD_TICK = CLOCK_FREQ / BAUD_RATE;

  reg [15:0] baud_counter;
  reg [3:0]  bit_index;
  reg [9:0]  tx_shift;             // [0]: start, [1]-[8]: data, [9]: stop
  reg        sending;

  always @(posedge sysclk or posedge rst) begin
    if (rst) begin
      baud_counter <= 0;
      bit_index    <= 0;
      tx_shift     <= 10'b1111111111;
      uart_txd_in  <= 1;  // Idle state is high
      sending      <= 0;
      tx_done      <= 0;
    end else begin
      if (tx_start && !sending) begin
        // Load shift register with frame: start bit (0), 8 data bits (LSB first), stop bit (1)
        tx_shift <= {1'b1, tx_data, 1'b0};
        sending  <= 1;
        baud_counter <= 0;
        bit_index <= 0;
        tx_done <= 0;
      end else if (sending) begin
        if (baud_counter < BAUD_TICK - 1) begin
          baud_counter <= baud_counter + 1;
        end else begin
          baud_counter <= 0;
          uart_txd_in <= tx_shift[bit_index];
          if (bit_index < 9) begin
            bit_index <= bit_index + 1;
          end else begin
            sending   <= 0;
            tx_done   <= 1;
          end
        end
      end else begin
        tx_done <= 0;
      end
    end
  end
endmodule

//////////////////////////////////////////////////////////////////////////////////
// Chua RNG Module (chua_rng)
// Digital simulation of Chua's circuit using Euler integration.
// Generates a 16-bit random number by extracting the lower 16 bits of v1.
// Fixed-point format: Q16 (32-bit signed; 16 integer and 16 fractional bits)
//////////////////////////////////////////////////////////////////////////////////
module _chua_rng (
    input              sysclk,   // renamed from clk
    input              rst,      // synchronous reset (active high)
    input [31:0] C1_seed,
    input [31:0] C2_seed,
    input [31:0] L_seed,
    output reg [15:0]  rnd       // 16-bit random number output
);
  // State registers: Q16 fixed-point (32-bit signed)
  reg signed [31:0] v1;  // voltage across C1
  reg signed [31:0] v2;  // voltage across C2
  reg signed [31:0] iL;  // current through the inductor

  // Parameter definitions (in Q16 format)

  parameter signed [31:0] inv_C1 = 32'd6554;   // ~65536/10
  parameter signed [31:0] inv_C2 = 32'd655;    // ~65536/100
  parameter signed [31:0] inv_L  = 32'd3641;   // ~65536/18

  parameter signed [31:0] R  = 32'd10000;  // resistor value (Q16)
  parameter signed [31:0] dt = 32'd66;      // time step ≈0.001 in Q16 (66/65536)
  // Nonlinear resistor (Chua diode) parameters in Q16.
  parameter signed [31:0] Ga = -32'd49152; // approx. -0.75 in Q16
  parameter signed [31:0] Gb =  32'd32768; // approx. 0.5 in Q16
  parameter signed [31:0] B  =  32'd8192;  // approx. 0.125 in Q16

  // Nonlinear function for Chua's diode (piecewise-linear)
  function signed [31:0] nonlinear;
    input signed [31:0] x;
    begin
      if (x > B)
        nonlinear = (Gb * x) >>> 16;
      else if (x < -B)
        nonlinear = (Gb * x) >>> 16;
      else
        nonlinear = (Ga * x) >>> 16;
    end
  endfunction

  reg signed [31:0] dv1, dv2, diL;
  reg signed [31:0] diff; // (v1 - v2)
  reg signed [31:0] term; // temporary term

  always @(posedge sysclk or posedge rst) begin
    if (rst) begin
      // Initialize state registers: seed values scaled to Q16.
      v1  <= C1_seed << 16;
      v2  <= C2_seed << 16;
      iL  <= L_seed  << 16;
      rnd <= 16'h0000;
    end else begin
      diff = v1 - v2;
      term = diff / R;
      dv1 = (inv_C1 * (term - nonlinear(v1))) >> 16;
      dv2 = (inv_C2 * ((-diff) / R + iL)) >> 16;
      diL = (inv_L * (-v2)) >> 16;

      // Euler integration update
      v1  <= v1  + ((dt * dv1) >> 16);
      v2  <= v2  + ((dt * dv2) >> 16);
      iL  <= iL  + ((dt * diL) >> 16);

      // Use lower 16 bits of v1 as random output
      rnd <= v1[15:0];
    end
  end
endmodule

//////////////////////////////////////////////////////////////////////////////////
// Top-Level Module (chua_uart_rng)
// Instantiates the Chua RNG and a UART transmitter.
// It latches a new 16-bit random number from the Chua simulation and sends it out via UART
// as two sequential 8-bit bytes (high byte first, then low byte).
// Ports are renamed to match the XDC constraint file:
//  - Clock input is now sysclk.
//  - UART TX output is now uart_txd_in.
//  - A dummy UART RX input, uart_rxd_out, is added.
//////////////////////////////////////////////////////////////////////////////////
module chua_uart_rng (
    input        sysclk,          // renamed from clk
    input        rst,
    output       uart_txd_in,     // matches constraint for UART TX output
    input        uart_rxd_out     // dummy port to satisfy board constraints; unused in this design
);
  // Wire from Chua RNG.
  wire [15:0] rnd;
  reg [15:0]  random_value;

  chua_rng rng_inst (
      .sysclk(sysclk),
      .rst(rst),
      .rnd(rnd)
  );

  // Signals for UART transmission.
  reg         tx_start;
  reg  [7:0]  tx_data;
  wire        tx_done;

  uart_tx uart_tx_inst (
      .sysclk(sysclk),
      .rst(rst),
      .tx_start(tx_start),
      .tx_data(tx_data),
      .uart_txd_in(uart_txd_in),
      .tx_done(tx_done)
  );

  // FSM to transmit the 16-bit random number in two sequential 8-bit segments.
  localparam STATE_IDLE       = 0;
  localparam STATE_SEND_HIGH  = 1;
  localparam STATE_WAIT_HIGH  = 2;
  localparam STATE_SEND_LOW   = 3;
  localparam STATE_WAIT_LOW   = 4;
  localparam STATE_DELAY      = 5;

  reg [2:0] state;
  reg [23:0] delay_counter; // Delay between transmissions.

  always @(posedge sysclk or posedge rst) begin
    if (rst) begin
      state         <= STATE_IDLE;
      tx_start      <= 0;
      tx_data       <= 8'd0;
      random_value  <= 16'd0;
      delay_counter <= 0;
    end else begin
      case (state)
        STATE_IDLE: begin
          // Latch current random value.
          random_value <= rnd;
          // Begin transmitting the high byte.
          tx_data  <= rnd[15:8];
          tx_start <= 1;
          state    <= STATE_SEND_HIGH;
        end
        STATE_SEND_HIGH: begin
          tx_start <= 0; // Clear start pulse.
          state    <= STATE_WAIT_HIGH;
        end
        STATE_WAIT_HIGH: begin
          if (tx_done) begin
            // High byte sent; now load low byte.
            tx_data  <= random_value[7:0];
            tx_start <= 1;
            state    <= STATE_SEND_LOW;
          end
        end
        STATE_SEND_LOW: begin
          tx_start <= 0;
          state    <= STATE_WAIT_LOW;
        end
        STATE_WAIT_LOW: begin
          if (tx_done) begin
            state         <= STATE_DELAY;
            delay_counter <= 0;
          end
        end
        STATE_DELAY: begin
          if (delay_counter < 24'd5000000) begin // Adjust delay as needed.
            delay_counter <= delay_counter + 1;
          end else begin
            state <= STATE_IDLE;
          end
        end
        default: state <= STATE_IDLE;
      endcase
    end
  end
endmodule

Lab_4/Lab4.srcs/sim_1/new/testbench.v
//////////////////////////////////////////////////////////////////////////////////
// Company: 
// Engineer: 
// 
// Create Date: 10.04.2025 12:40:17
// Design Name: 
// Module Name: testbench
// Project Name: 
// Target Devices: 
// Tool Versions: 
// Description: 
// 
// Dependencies: 
// 
// Revision:
// Revision 0.01 - File Created
// Additional Comments:
// 
//////////////////////////////////////////////////////////////////////////////////


`timescale 1ns/1ps
module tb_chua_uart_rng;
  // Declare testbench signals.
  reg         sysclk;
  reg         rst;
  reg [31:0]  seed_1;
  reg [31:0]  seed_2;
  reg [31:0]  seed_3;
  wire [15:0] rnd_out;

  // Instantiate the Chua RNG module.
  _chua_rng rng_uut (
    .sysclk(sysclk),
    .C1_seed(seed_1),
    .C2_seed(seed_2),
    .L_seed(seed_3),
    .rst(rst),
    .rnd(rnd_out)
  );

  // Combined initial block using one for loop.
  initial begin
    // Initialize values.
    sysclk = 0;
    seed_1 = 10;
    seed_2 = 100;
    seed_3 = 1;
    rst = 0;

    // Dump all variables for waveform inspection.
    $dumpfile("simulation.vcd");
    $dumpvars(0, tb_chua_uart_rng);

    // Run the simulation loop. 
    // For example, if you want to run for 10,000,000 ns using a 5 ns time step:
    // Total iterations = 10,000,000 ns / 5 ns = 2,000,000 iterations.
    for (integer i = 0; i < 2000000; i = i + 1) begin
      #5;                 // Delay of 5 ns per iteration.
      sysclk = ~sysclk;   // Toggle the clock every 5 ns.

      // Update seed_2 every 10 ns.
      // Since our time step is 5 ns, do it on every second iteration.
      if (i % 2 == 0)
        seed_2 = seed_2 + 10000;

      // Toggle reset every 40 ns.
      // (40 ns / 5 ns = 8 iterations; every 8 iterations, toggle rst).
      if (i % 8 == 0)
        rst = ~rst;
    end

    // End simulation
    $stop;
  end

endmodule

Lab_4/Lab4.sim/sim_1/behav/xsim/simulation.vcd
$date
   Thu Apr 10 18:16:26 2025
$end

$version
  2024.2.0
  $dumpfile ("simulation.vcd") 
$end

$timescale
  1ps
$end

$scope module tb_chua_uart_rng $end
$var reg 1 ! sysclk $end
$var reg 1 " rst $end
$var reg 32 # seed_1 [31:0] $end
$var reg 32 $ seed_2 [31:0] $end
$var reg 32 % seed_3 [31:0] $end
$var wire 16 & rnd_out [15:0] $end
$scope module rng_uut $end
$var wire 1 ' sysclk $end
$var wire 1 ( rst $end
$var wire 32 ) C1_seed [31:0] $end
$var wire 32 * C2_seed [31:0] $end
$var wire 32 + L_seed [31:0] $end
$var reg 16 , rnd [15:0] $end
$var reg 32 - v1 [31:0] $end
$var reg 32 . v2 [31:0] $end
$var reg 32 / iL [31:0] $end
$var reg 32 0 dv1 [31:0] $end
$var reg 32 1 dv2 [31:0] $end
$var reg 32 2 diL [31:0] $end
$var reg 32 3 diff [31:0] $end
$var reg 32 4 term [31:0] $end
$scope function nonlinear $end
$var reg 32 5 nonlinear [31:0] $end
$var reg 32 6 x [31:0] $end
$upscope $end
$upscope $end
$scope begin Block58_2 $end
$var integer 32 7 i [31:0] $end
$upscope $end
$upscope $end
$enddefinitions $end

#0
$dumpvars
0!
0"
b1010 #
b1100100 $
b1 %
bx &
0'
0(
b1010 )
b1100100 *
b1 +
bx ,
bx -
bx .
bx /
bx 0
bx 1
bx 2
bx 3
bx 4
bx 5
bx 6
b0 7
$end

#5000
1!
1"
b10011101110100 $
b0 &
1'
1(
b10011101110100 *
b0 ,
b10100000000000000000 -
b100111011101000000000000000000 .
b10000000000000000 /
b1 7

#10000
0!
0'
b10 7

#15000
1!
b100111010000100 $
1'
b100111010000100 *
b1001110100001000000000000000000 .
b11 7

#20000
0!
0'
b100 7

#25000
1!
b111010110010100 $
1'
b111010110010100 *
b1110101100101000000000000000000 .
b101 7

#30000
0!
0'
b110 7

#35000
1!
b1001110010100100 $
1'
b1001110010100100 *
b10011100101001000000000000000000 .
b111 7

#40000
0!
0'
b1000 7

#45000
1!
0"
b1100001110110100 $
1'
0(
b1100001110110100 *
b10100000000000010000 -
b10011100101001000000000001000000 .
b10000000000001010 /
b100000100100101 0
b1111110000001100 1
b10011101111100 2
b1100011011001100000000000000000 3
b101000101101101010 4
b0 5
b10100000000000000000 6
b1001 7

#50000
0!
0'
b1010 7

#55000
1!
b1110101011000100 $
b10000 &
1'
b1110101011000100 *
b10000 ,
b10100000000000100000 -
b10011100101001000000000010000000 .
b10000000000010100 /
b100000100100100 0
b10011101111000 2
b1100011011001011111111111010000 3
b1000 5
b10100000000000010000 6
b1011 7

#60000
0!
0'
b1100 7

#65000
1!
b10001000111010100 $
b100000 &
1'
b10001000111010100 *
b100000 ,
b10100000000000110000 -
b10011100101001000000000011000000 .
b10000000000011110 /
b100000100100011 0
b10011101110100 2
b1100011011001011111111110100000 3
b10000 5
b10100000000000100000 6
b1101 7

#70000
0!
0'
b1110 7

#75000
1!
b10011100011100100 $
b110000 &
1'
b10011100011100100 *
b110000 ,
b10100000000001000000 -
b10011100101001000000000100000000 .
b10000000000101000 /
b100000100100010 0
b10011101110001 2
b1100011011001011111111101110000 3
b11000 5
b10100000000000110000 6
b1111 7

#80000
0!
0'
b10000 7

#85000
1!
1"
b10101111111110100 $
b0 &
1'
1(
b10101111111110100 *
b0 ,
b10100000000000000000 -
b1011111111101000000000000000000 .
b10000000000000000 /
b10001 7

#90000
0!
0'
b10010 7

#95000
1!
b11000011100000100 $
1'
b11000011100000100 *
b10000111000001000000000000000000 .
b10011 7

#100000
0!
0'
b10100 7

#105000
1!
b11010111000010100 $
1'
b11010111000010100 *
b10101110000101000000000000000000 .
b10101 7

#110000
0!
0'
b10110 7

#115000
1!
b11101010100100100 $
1'
b11101010100100100 *
b11010101001001000000000000000000 .
b10111 7

#120000
0!
0'
b11000 7

#125000
1!
0"
b11111110000110100 $
1'
0(
b11111110000110100 *
b10100000000000000111 -
b11010101001001000000000001000001 .
b10000000000100101 /
b1110000011101 0
b1111111110111111 1
b1001001011111100 2
b101010111001100000000000000000 3
b10001100100100011 4
b0 5
b10100000000000000000 6
b11001 7

#130000
0!
0'
b11010 7

#135000
1!
b100010001101000100 $
b111 &
1'
b100010001101000100 *
b111 ,
b10100000000000001110 -
b11010101001001000000000010000010 .
b10000000001001010 /
b1111111111000000 1
b1001001011111000 2
b101010111001011111111111000110 3
b11 5
b10100000000000000111 6
b11011 7

#140000
0!
0'
b11100 7

#145000
1!
b100100101001010100 $
b1110 &
1'
b100100101001010100 *
b1110 ,
b10100000000000010101 -
b11010101001001000000000011000011 .
b10000000001101111 /
b1110000011100 0
b1001001011110100 2
b101010111001011111111110001100 3
b111 5
b10100000000000001110 6
b11101 7

#150000
0!
0'
b11110 7

#155000
1!
b100111000101100100 $
b10101 &
1'
b100111000101100100 *
b10101 ,
b10100000000000011100 -
b11010101001001000000000100000100 .
b10000000010010100 /
b1001001011110001 2
b101010111001011111111101010010 3
b1010 5
b10100000000000010101 6
b11111 7

#160000
0!
0'
b100000 7

#165000
1!
1"
b101001100001110100 $
b0 &
1'
1(
b101001100001110100 *
b0 ,
b10100000000000000000 -
b10011000011101000000000000000000 .
b10000000000000000 /
b100001 7

#170000
0!
0'
b100010 7

#175000
1!
b101011111110000100 $
1'
b101011111110000100 *
b10111111100001000000000000000000 .
b100011 7

#180000
0!
0'
b100100 7

#185000
1!
b101110011010010100 $
1'
b101110011010010100 *
b11100110100101000000000000000000 .
b100101 7

#190000
0!
0'
b100110 7

#195000
1!
b110000110110100100 $
1'
b110000110110100100 *
b1101101001000000000000000000 .
b100111 7

#200000
0!
0'
b101000 7

#205000
1!
0"
b110011010010110100 $
1'
0(
b110011010010110100 *
b10100000000000111111 -
b10000000001000001 /
b1111011100010101 0
b1101110011 1
b1111111001111100 2
b11110010011001100000000000000000 3
b11111111111111111010011011011101 4
b0 5
b10100000000000000000 6
b101001 7

#210000
0!
0'
b101010 7

#215000
1!
b110101101111000100 $
b111111 &
1'
b110101101111000100 *
b111111 ,
b10100000000001111110 -
b10000000010000010 /
b1111011100010010 0
b11110010011001100000000000111111 3
b11111 5
b10100000000000111111 6
b101011 7

#220000
0!
0'
b101100 7

#225000
1!
b111000001011010100 $
b1111110 &
1'
b111000001011010100 *
b1111110 ,
b10100000000010111101 -
b10000000011000011 /
b1111011100001111 0
b1101110100 1
b11110010011001100000000001111110 3
b111111 5
b10100000000001111110 6
b101101 7

#230000
0!
0'
b101110 7

#235000
1!
b111010100111100100 $
b10111101 &
1'
b111010100111100100 *
b10111101 ,
b10100000000011111100 -
b10000000100000100 /
b1111011100001100 0
b1101110101 1
b11110010011001100000000010111101 3
b1011110 5
b10100000000010111101 6
b101111 7

#240000
0!
0'
b110000 7

#245000
1!
1"
b111101000011110100 $
b0 &
1'
1(
b111101000011110100 *
b0 ,
b10100000000000000000 -
b11010000111101000000000000000000 .
b10000000000000000 /
b110001 7

#250000
0!
0'
b110010 7

#255000
1!
b111111100000000100 $
1'
b111111100000000100 *
b11111000000001000000000000000000 .
b110011 7

#260000
0!
0'
b110100 7

#265000
1!
b1000001111100010100 $
1'
b1000001111100010100 *
b11111000101000000000000000000 .
b110101 7

#270000
0!
0'
b110110 7

#275000
1!
b1000100011000100100 $
1'
b1000100011000100100 *
b1000110001001000000000000000000 .
b110111 7

#280000
0!
0'
b111000 7

#285000
1!
0"
b1000110110100110100 $
1'
0(
b1000110110100110100 *
b10100000000000110110 -
b1000110001001000000000000000001 .
b10000000000011011 /
b1101001000001110 0
b11100100110 1
b110100111111100 2
b10111001111001100000000000000000 3
b11111111111111100011010010010110 4
b0 5
b10100000000000000000 6
b111001 7

#290000
0!
0'
b111010 7

#295000
1!
b1001001010001000100 $
b110110 &
1'
b1001001010001000100 *
b110110 ,
b10100000000001101100 -
b1000110001001000000000000000010 .
b10000000000110110 /
b1101001000001011 0
b110100111111011 2
b10111001111001100000000000110101 3
b11011 5
b10100000000000110110 6
b111011 7

#300000
0!
0'
b111100 7

#305000
1!
b1001011101101010100 $
b1101100 &
1'
b1001011101101010100 *
b1101100 ,
b10100000000010100010 -
b1000110001001000000000000000011 .
b10000000001010001 /
b1101001000001000 0
b10111001111001100000000001101010 3
b110110 5
b10100000000001101100 6
b111101 7

#310000
0!
0'
b111110 7

#315000
1!
b1001110001001100100 $
b10100010 &
1'
b1001110001001100100 *
b10100010 ,
b10100000000011011000 -
b1000110001001000000000000000100 .
b10000000001101100 /
b1101001000000110 0
b11100100111 1
b10111001111001100000000010011111 3
b1010001 5
b10100000000010100010 6
b111111 7

#320000
0!
0'
b1000000 7

#325000
1!
1"
b1010000100101110100 $
b0 &
1'
1(
b1010000100101110100 *
b0 ,
b10100000000000000000 -
b1001011101000000000000000000 .
b10000000000000000 /
b1000001 7

#330000
0!
0'
b1000010 7

#335000
1!
b1010011000010000100 $
1'
b1010011000010000100 *
b110000100001000000000000000000 .
b1000011 7

#340000
0!
0'
b1000100 7

#345000
1!
b1010101011110010100 $
1'
b1010101011110010100 *
b1010111100101000000000000000000 .
b1000101 7

#350000
0!
0'
b1000110 7

#355000
1!
b1010111111010100100 $
1'
b1010111111010100100 *
b1111110101001000000000000000000 .
b1000111 7

#360000
0!
0'
b1001000 7

#365000
1!
0"
b1011010010110110100 $
1'
0(
b1011010010110110100 *
b10100000000000101100 -
b1111110101001000000000000000010 .
b10000000000110111 /
b1010110100000110 0
b101011011001 1
b1101010101111100 2
b10000001011001100000000000000000 3
b11111111111111001100001001001110 4
b0 5
b10100000000000000000 6
b1001001 7

#370000
0!
0'
b1001010 7

#375000
1!
b1011100110011000100 $
b101100 &
1'
b1011100110011000100 *
b101100 ,
b10100000000001011000 -
b1111110101001000000000000000100 .
b10000000001101110 /
b1010110100000100 0
b101011011010 1
b1101010101111011 2
b10000001011001100000000000101010 3
b10110 5
b10100000000000101100 6
b1001011 7

#380000
0!
0'
b1001100 7

#385000
1!
b1011111001111010100 $
b1011000 &
1'
b1011111001111010100 *
b1011000 ,
b10100000000010000100 -
b1111110101001000000000000000110 .
b10000000010100101 /
b1010110100000010 0
b10000001011001100000000001010100 3
b101100 5
b10100000000001011000 6
b1001101 7

#390000
0!
0'
b1001110 7

#395000
1!
b1100001101011100100 $
b10000100 &
1'
b1100001101011100100 *
b10000100 ,
b10100000000010110000 -
b1111110101001000000000000001000 .
b10000000011011100 /
b1010110011111111 0
b101011011011 1
b10000001011001100000000001111110 3
b1000010 5
b10100000000010000100 6
b1001111 7

#400000
0!
0'
b1010000 7

#405000
1!
1"
b1100100000111110100 $
b0 &
1'
1(
b1100100000111110100 *
b0 ,
b10100000000000000000 -
b1000001111101000000000000000000 .
b10000000000000000 /
b1010001 7

#410000
0!
0'
b1010010 7

#415000
1!
b1100110100100000100 $
1'
b1100110100100000100 *
b1101001000001000000000000000000 .
b1010011 7

#420000
0!
0'
b1010100 7

#425000
1!
b1101001000000010100 $
1'
b1101001000000010100 *
b10010000000101000000000000000000 .
b1010101 7

#430000
0!
0'
b1010110 7

#435000
1!
b1101011011100100100 $
1'
b1101011011100100100 *
b10110111001001000000000000000000 .
b1010111 7

#440000
0!
0'
b1011000 7

#445000
1!
0"
b1101101111000110100 $
1'
0(
b1101101111000110100 *
b10100000000000001100 -
b10110111001001000000000001000001 .
b10000000000010000 /
b10111111000111 0
b1111110111001000 1
b100000011111100 2
b1001000111001100000000000000000 3
b11101110110111111 4
b0 5
b10100000000000000000 6
b1011001 7

#450000
0!
0'
b1011010 7

#455000
1!
b1110000010101000100 $
b1100 &
1'
b1110000010101000100 *
b1100 ,
b10100000000000011000 -
b10110111001001000000000010000010 .
b10000000000100000 /
b10111111000110 0
b100000011111000 2
b1001000111001011111111111001011 3
b110 5
b10100000000000001100 6
b1011011 7

#460000
0!
0'
b1011100 7

#465000
1!
b1110010110001010100 $
b11000 &
1'
b1110010110001010100 *
b11000 ,
b10100000000000100100 -
b10110111001001000000000011000011 .
b10000000000110000 /
b10111111000101 0
b100000011110100 2
b1001000111001011111111110010110 3
b1100 5
b10100000000000011000 6
b1011101 7

#470000
0!
0'
b1011110 7

#475000
1!
b1110101001101100100 $
b100100 &
1'
b1110101001101100100 *
b100100 ,
b10100000000000110000 -
b10110111001001000000000100000100 .
b10000000001000000 /
b1111110111001001 1
b100000011110001 2
b1001000111001011111111101100001 3
b10010 5
b10100000000000100100 6
b1011111 7

#480000
0!
0'
b1100000 7

#485000
1!
1"
b1110111101001110100 $
b0 &
1'
1(
b1110111101001110100 *
b0 ,
b10100000000000000000 -
b1111010011101000000000000000000 .
b10000000000000000 /
b1100001 7

#490000
0!
0'
b1100010 7

#495000
1!
b1111010000110000100 $
1'
b1111010000110000100 *
b10100001100001000000000000000000 .
b1100011 7

#500000
0!
0'
b1100100 7

#505000
1!
b1111100100010010100 $
1'
b1111100100010010100 *
b11001000100101000000000000000000 .
b1100101 7

#510000
0!
0'
b1100110 7

#515000
1!
b1111110111110100100 $
1'
b1111110111110100100 *
b11101111101001000000000000000000 .
b1100111 7

#520000
0!
0'
b1101000 7

#525000
1!
0"
b10000001011010110100 $
1'
0(
b10000001011010110100 *
b10100000000000000010 -
b10000000000101100 /
b101010111111 0
b101111100 1
b1010110001111100 2
b10000011001100000000000000000 3
b110101101111000 4
b0 5
b10100000000000000000 6
b1101001 7

#530000
0!
0'
b1101010 7

#535000
1!
b10000011110111000100 $
b10 &
1'
b10000011110111000100 *
b10 ,
b10100000000000000100 -
b10000000001011000 /
b10000011001100000000000000010 3
b1 5
b10100000000000000010 6
b1101011 7

#540000
0!
0'
b1101100 7

#545000
1!
b10000110010011010100 $
b100 &
1'
b10000110010011010100 *
b100 ,
b10100000000000000110 -
b10000000010000100 /
b10000011001100000000000000100 3
b10 5
b10100000000000000100 6
b1101101 7

#550000
0!
0'
b1101110 7

#555000
1!
b10001000101111100100 $
b110 &
1'
b10001000101111100100 *
b110 ,
b10100000000000001000 -
b10000000010110000 /
b101111101 1
b10000011001100000000000000110 3
b11 5
b10100000000000000110 6
b1101111 7

#560000
0!
0'
b1110000 7

#565000
1!
1"
b10001011001011110100 $
b0 &
1'
1(
b10001011001011110100 *
b0 ,
b10100000000000000000 -
b10110010111101000000000000000000 .
b10000000000000000 /
b1110001 7

#570000
0!
0'
b1110010 7

#575000
1!
b10001101101000000100 $
1'
b10001101101000000100 *
b11011010000001000000000000000000 .
b1110011 7

#580000
0!
0'
b1110100 7

#585000
1!
b10010000000100010100 $
1'
b10010000000100010100 *
b1000101000000000000000000 .
b1110101 7

#590000
0!
0'
b1110110 7

#595000
1!
b10010010100000100100 $
1'
b10010010100000100100 *
b101000001001000000000000000000 .
b1110111 7

#600000
0!
0'
b1111000 7

#605000
1!
0"
b10010100111100110100 $
1'
0(
b10010100111100110100 *
b10100000000000111011 -
b101000001001000000000000000001 .
b10000000000000110 /
b1110010110110111 0
b10100101111 1
b1011111111100 2
b11010111111001100000000000000000 3
b11111111111111101111100100110001 4
b0 5
b10100000000000000000 6
b1111001 7

#610000
0!
0'
b1111010 7

#615000
1!
b10010111011001000100 $
b111011 &
1'
b10010111011001000100 *
b111011 ,
b10100000000001110110 -
b101000001001000000000000000010 .
b10000000000001100 /
b1110010110110100 0
b1011111111011 2
b11010111111001100000000000111010 3
b11101 5
b10100000000000111011 6
b1111011 7

#620000
0!
0'
b1111100 7

#625000
1!
b10011001110101010100 $
b1110110 &
1'
b10011001110101010100 *
b1110110 ,
b10100000000010110001 -
b101000001001000000000000000011 .
b10000000000010010 /
b1110010110110001 0
b11010111111001100000000001110100 3
b111011 5
b10100000000001110110 6
b1111101 7

#630000
0!
0'
b1111110 7

#635000
1!
b10011100010001100100 $
b10110001 &
1'
b10011100010001100100 *
b10110001 ,
b10100000000011101100 -
b101000001001000000000000000100 .
b10000000000011000 /
b1110010110101110 0
b11010111111001100000000010101110 3
b1011000 5
b10100000000010110001 6
b1111111 7

#640000
0!
0'
b10000000 7

#645000
1!
1"
b10011110101101110100 $
b0 &
1'
1(
b10011110101101110100 *
b0 ,
b10100000000000000000 -
b11101011011101000000000000000000 .
b10000000000000000 /
b10000001 7

#650000
0!
0'
b10000010 7

#655000
1!
b10100001001010000100 $
1'
b10100001001010000100 *
b10010100001000000000000000000 .
b10000011 7

#660000
0!
0'
b10000100 7

#665000
1!
b10100011100110010100 $
1'
b10100011100110010100 *
b111001100101000000000000000000 .
b10000101 7

#670000
0!
0'
b10000110 7

#675000
1!
b10100110000010100100 $
1'
b10100110000010100100 *
b1100000101001000000000000000000 .
b10000111 7

#680000
0!
0'
b10001000 7

#685000
1!
0"
b10101000011110110100 $
1'
0(
b10101000011110110100 *
b10100000000000110001 -
b1100000101001000000000000000010 .
b10000000000100001 /
b1100000010110000 0
b100011100010 1
b1000001101111100 2
b10011111011001100000000000000000 3
b11111111111111011000011011101010 4
b0 5
b10100000000000000000 6
b10001001 7

#690000
0!
0'
b10001010 7

#695000
1!
b10101010111011000100 $
b110001 &
1'
b10101010111011000100 *
b110001 ,
b10100000000001100010 -
b1100000101001000000000000000100 .
b10000000001000010 /
b1100000010101101 0
b100011100011 1
b1000001101111011 2
b10011111011001100000000000101111 3
b11000 5
b10100000000000110001 6
b10001011 7

#700000
0!
0'
b10001100 7

#705000
1!
b10101101010111010100 $
b1100010 &
1'
b10101101010111010100 *
b1100010 ,
b10100000000010010011 -
b1100000101001000000000000000110 .
b10000000001100011 /
b1100000010101011 0
b10011111011001100000000001011110 3
b110001 5
b10100000000001100010 6
b10001101 7

#710000
0!
0'
b10001110 7

#715000
1!
b10101111110011100100 $
b10010011 &
1'
b10101111110011100100 *
b10010011 ,
b10100000000011000100 -
b1100000101001000000000000001000 .
b10000000010000100 /
b1100000010101000 0
b10011111011001100000000010001101 3
b1001001 5
b10100000000010010011 6
b10001111 7

#720000
0!
0'
b10010000 7

#725000
1!
1"
b10110010001111110100 $
b0 &
1'
1(
b10110010001111110100 *
b0 ,
b10100000000000000000 -
b100011111101000000000000000000 .
b10000000000000000 /
b10010001 7

#730000
0!
0'
b10010010 7

#735000
1!
b10110100101100000100 $
1'
b10110100101100000100 *
b1001011000001000000000000000000 .
b10010011 7

#740000
0!
0'
b10010100 7

#745000
1!
b10110111001000010100 $
1'
b10110111001000010100 *
b1110010000101000000000000000000 .
b10010101 7

#750000
0!
0'
b10010110 7

#755000
1!
b10111001100100100100 $
1'
b10111001100100100100 *
b10011001001001000000000000000000 .
b10010111 7

#760000
0!
0'
b10011000 7

#765000
1!
0"
b10111100000000110100 $
1'
0(
b10111100000000110100 *
b10100000000000010001 -
b10011001001001000000000001000000 .
b10000000000111101 /
b100001101110000 0
b1111101111010001 1
b1110111011111100 2
b1100110111001100000000000000000 3
b101010001001011010 4
b0 5
b10100000000000000000 6
b10011001 7

#770000
0!
0'
b10011010 7

#775000
1!
b10111110011101000100 $
b10001 &
1'
b10111110011101000100 *
b10001 ,
b10100000000000100010 -
b10011001001001000000000010000000 .
b10000000001111010 /
b100001101101111 0
b1111101111010010 1
b1110111011111000 2
b1100110111001011111111111010001 3
b1000 5
b10100000000000010001 6
b10011011 7

#780000
0!
0'
b10011100 7

#785000
1!
b11000000111001010100 $
b100010 &
1'
b11000000111001010100 *
b100010 ,
b10100000000000110011 -
b10011001001001000000000011000000 .
b10000000010110111 /
b100001101101110 0
b1110111011110100 2
b1100110111001011111111110100010 3
b10001 5
b10100000000000100010 6
b10011101 7

#790000
0!
0'
b10011110 7

#795000
1!
b11000011010101100100 $
b110011 &
1'
b11000011010101100100 *
b110011 ,
b10100000000001000100 -
b10011001001001000000000100000000 .
b10000000011110100 /
b100001101101101 0
b1111101111010011 1
b1110111011110001 2
b1100110111001011111111101110011 3
b11001 5
b10100000000000110011 6
b10011111 7

#800000
0!
0'
b10100000 7

#805000
1!
1"
b11000101110001110100 $
b0 &
1'
1(
b11000101110001110100 *
b0 ,
b10100000000000000000 -
b1011100011101000000000000000000 .
b10000000000000000 /
b10100001 7

#810000
0!
0'
b10100010 7

#815000
1!
b11001000001110000100 $
1'
b11001000001110000100 *
b10000011100001000000000000000000 .
b10100011 7

#820000
0!
0'
b10100100 7

#825000
1!
b11001010101010010100 $
1'
b11001010101010010100 *
b10101010100101000000000000000000 .
b10100101 7

#830000
0!
0'
b10100110 7

#835000
1!
b11001101000110100100 $
1'
b11001101000110100100 *
b11010001101001000000000000000000 .
b10100111 7

#840000
0!
0'
b10101000 7

#845000
1!
0"
b11001111100010110100 $
1'
0(
b11001111100010110100 *
b10100000000000000111 -
b11010001101001000000000001000001 .
b10000000000010111 /
b1111001101000 0
b1111111110000100 1
b101101001111100 2
b101110011001100000000000000000 3
b10011000000010011 4
b0 5
b10100000000000000000 6
b10101001 7

#850000
0!
0'
b10101010 7

